{
    "CheckMaxHandSize": {
        "Title": "Discard until you have {arg0} Cards - {arg1} Cards remaining",
        "MustShowInCenter": false
    },
    "CheckSlots": {
        "Title": "{arg0} Slots is full, choose Supply To Discard",
        "MustShowInCenter": true
    },
    "ChooseInvestigator": {
        "Title": "Choose Investigator to play his turn",
        "MustShowInCenter": true
    },
    "CommitCardsChallenge": {
        "Title": "Commit cards to this Challenge",
        "MustShowInCenter": false
    },
    "Mulligan": {
        "Title": "Discard Cards to replace them",
        "MustShowInCenter": false
    },
    "OneInvestigatorTurn": {
        "Title": "{arg0} plays his Turn - {arg1} Actions remaining",
        "MustShowInCenter": false
    },
    "PayHintsToGoal": {
        "Title": "Choose Investigator to pay Hints to the Goal",
        "MustShowInCenter": true
    },
    "ShareDamageAndFear": {
        "Title": "Deal {arg0}Damage - {arg1}Fear",
        "MustShowInCenter": true
    },
    "Card01135": {
        "Title": "Choose one",
        "MustShowInCenter": true
    },
    "Card01158": {
        "Title": "Choose one - {arg0} choices remaining",
        "MustShowInCenter": true
    },
    "Card01167": {
        "Title": "Discard Supply",
        "MustShowInCenter": true
    },
    "Card01174": {
        "Title": "Choose Challenge type",
        "MustShowInCenter": true
    },
    "Card01596": {
        "Title": "Choose Card, the rest are discarded",
        "MustShowInCenter": true
    },
    "Card01524": {
        "Title": "Choose Place",
        "MustShowInCenter": true
    },
    "Card01178": {
        "Title": "Choose one",
        "MustShowInCenter": true
    },
    "Card01526": {
        "Title": "Choose Firearm",
        "MustShowInCenter": true
    },
    "Card01543": {
        "Title": "Choose Investigator",
        "MustShowInCenter": true
    },
    "Card01550": {
        "Title": "Choose Place",
        "MustShowInCenter": true
    },
    "Card01551": {
        "Title": "Choose Creature",
        "MustShowInCenter": true
    },
    "Card01552": {
        "Title": "Choose Creature",
        "MustShowInCenter": true
    },
    "Card01566": {
        "Title": "Choose Creature",
        "MustShowInCenter": true
    },
    "Card01568": {
        "Title": "Choose Creature",
        "MustShowInCenter": true
    },
    "Card01569": {
        "Title": "Choose Creature",
        "MustShowInCenter": true
    },
    "Card01685": {
        "Title": "Choose Place",
        "MustShowInCenter": true
    },
    "Card01685-2": {
        "Title": "Choose Place",
        "MustShowInCenter": true
    },
    "Card01138": {
        "Title": "Choose Card to discard - {arg0} Cards remaining",
        "MustShowInCenter": false
    },
    "Card01110": {
        "Title": "Choose decision",
        "MustShowInCenter": true
    },
    "Card01502": {
        "Title": "Choose Tome",
        "MustShowInCenter": true
    },
    "Card01504": {
        "Title": "Choose Creature",
        "MustShowInCenter": true
    },
    "Card01505": {
        "Title": "Choose Card to discard",
        "MustShowInCenter": true
    },
    "Card01127": {
        "Title": "Choose Support",
        "MustShowInCenter": true
    },
    "Card01129": {
        "Title": "Choose Tome or Spell",
        "MustShowInCenter": true
    },
    "Card01518": {
        "Title": "Choose Creature",
        "MustShowInCenter": true
    },
    "Card01519": {
        "Title": "Choose Investigator",
        "MustShowInCenter": true
    },
    "Card01528": {
        "Title": "Choose Creature",
        "MustShowInCenter": true
    },
    "Card01531": {
        "Title": "Choose Investigator",
        "MustShowInCenter": true
    },
    "Card01531-2": {
        "Title": "Choose Card to draw",
        "MustShowInCenter": true
    },
    "Card01532": {
        "Title": "Choose Tome",
        "MustShowInCenter": true
    },
    "Card01535": {
        "Title": "Choose Investigator",
        "MustShowInCenter": true
    },
    "Card01105": {
        "Title": "Choose decision",
        "MustShowInCenter": true
    },
    "Card01542": {
        "Title": "Choose Investigator",
        "MustShowInCenter": true
    },
    "Card01542-1": {
        "Title": "Choose Skill",
        "MustShowInCenter": true
    },
    "Card01545": {
        "Title": "Choose Place",
        "MustShowInCenter": true
    },
    "Card01555": {
        "Title": "Choose Place",
        "MustShowInCenter": true
    },
    "Card01561": {
        "Title": "Choose deck",
        "MustShowInCenter": true
    },
    "Card01561-1": {
        "Title": "Choose Card to return",
        "MustShowInCenter": true
    },
    "Card01563": {
        "Title": "Choose Spell",
        "MustShowInCenter": true
    },
    "Card01570": {
        "Title": "Choose Spell",
        "MustShowInCenter": true
    },
    "Card01571": {
        "Title": "Choose Token",
        "MustShowInCenter": true
    },
    "Card01573": {
        "Title": "Choose Item",
        "MustShowInCenter": true
    },
    "Card01576": {
        "Title": "Choose Creature",
        "MustShowInCenter": true
    },
    "Card01582": {
        "Title": "Choose Creature",
        "MustShowInCenter": true
    },
    "Card01587": {
        "Title": "Choose Place",
        "MustShowInCenter": true
    },
    "Card01683": {
        "Title": "Choose Card to Health",
        "MustShowInCenter": true
    },
    "Card01686": {
        "Title": "Choose Investigator",
        "MustShowInCenter": true
    },
    "Card01686-1": {
        "Title": "Choose Card to draw",
        "MustShowInCenter": true
    },
    "Card01686-2": {
        "Title": "Spend one Secret to play this Card",
        "MustShowInCenter": true
    },
    "Card01687": {
        "Title": "Choose Place",
        "MustShowInCenter": true
    },
    "Card01689": {
        "Title": "Choose Place",
        "MustShowInCenter": true
    },
    "Card01690": {
        "Title": "Choose deck",
        "MustShowInCenter": true
    },
    "Card01690-1": {
        "Title": "Choose Card to return",
        "MustShowInCenter": true
    },
    "Card01691": {
        "Title": "Choose Creature",
        "MustShowInCenter": true
    },
    "CardWeapon": {
        "Title": "Choose Creature",
        "MustShowInCenter": true
    },
    "Card01581": {
        "Title": "Choose Place",
        "MustShowInCenter": true
    },
    "OptativeReactions": {
        "Title": "Choose Card to play",
        "MustShowInCenter": true
    },
    "TestsPurpose": {
        "Title": "Choose",
        "MustShowInCenter": true
    }
}